{
  "$schema": "https://developer.microsoft.com/json-schemas/fabric/item/report/definition/bookmark/1.4.0/schema.json",
  "displayName": "5 Open",
  "name": "605c0a989c000c281b6b",
  "options": {
    "applyOnlyToTargetVisuals": true,
    "targetVisualNames": [
      "3743185304e282a60602",
      "e1cfb32d7b7737a45259",
      "d5ebefc3020007821d9b",
      "360a3450800c8528689c",
      "074b044b0f36b51d3980",
      "60dfeca901652007d6be",
      "1d6c695259bac0a40741",
      "3f460a5c6a42d39921dc",
      "07c2a7040a9526e0e520",
      "b8f0e5e10b8ea026dd63",
      "35ec6870ee140772c0b0",
      "dde7498fb9766232a0ca",
      "1b34b4636487d0e104c0"
    ],
    "suppressData": true
  },
  "explorationState": {
    "version": "1.3",
    "activeSection": "8d6d0fc9d2731c8d03b3",
    "sections": {
      "8d6d0fc9d2731c8d03b3": {
        "visualContainers": {
          "b4c03ec50402c634e0bb": {
            "singleVisual": {
              "visualType": "actionButton",
              "objects": {}
            }
          },
          "dde7498fb9766232a0ca": {
            "singleVisual": {
              "visualType": "actionButton",
              "objects": {}
            }
          },
          "1b34b4636487d0e104c0": {
            "singleVisual": {
              "visualType": "shape",
              "objects": {}
            }
          },
          "b4e760cac93e09a103ea": {
            "singleVisual": {
              "visualType": "textbox",
              "objects": {}
            }
          },
          "d5ebefc3020007821d9b": {
            "singleVisual": {
              "visualType": "actionButton",
              "objects": {}
            }
          },
          "360a3450800c8528689c": {
            "singleVisual": {
              "visualType": "actionButton",
              "objects": {}
            }
          },
          "074b044b0f36b51d3980": {
            "filters": {
              "byExpr": [
                {
                  "name": "51103e832665e3aabb5e",
                  "type": "RelativeDate",
                  "filter": {
                    "Version": 2,
                    "From": [
                      {
                        "Name": "d",
                        "Entity": "Dim Extract Date",
                        "Type": 0
                      }
                    ],
                    "Where": [
                      {
                        "Condition": {
                          "Between": {
                            "Expression": {
                              "Column": {
                                "Expression": {
                                  "SourceRef": {
                                    "Source": "d"
                                  }
                                },
                                "Property": "Extract Date"
                              }
                            },
                            "LowerBound": {
                              "DateSpan": {
                                "Expression": {
                                  "DateAdd": {
                                    "Expression": {
                                      "DateAdd": {
                                        "Expression": {
                                          "Now": {}
                                        },
                                        "Amount": 1,
                                        "TimeUnit": 0
                                      }
                                    },
                                    "Amount": -5,
                                    "TimeUnit": 3
                                  }
                                },
                                "TimeUnit": 0
                              }
                            },
                            "UpperBound": {
                              "DateSpan": {
                                "Expression": {
                                  "Now": {}
                                },
                                "TimeUnit": 0
                              }
                            }
                          }
                        }
                      }
                    ]
                  },
                  "expression": {
                    "Column": {
                      "Expression": {
                        "SourceRef": {
                          "Entity": "Dim Extract Date"
                        }
                      },
                      "Property": "Extract Date"
                    }
                  },
                  "howCreated": 1
                },
                {
                  "name": "aef1d277fd35d356cd08",
                  "type": "Categorical",
                  "expression": {
                    "Column": {
                      "Expression": {
                        "SourceRef": {
                          "Entity": "Dim Extract Date"
                        }
                      },
                      "Property": "Slicer MMM YYYY"
                    }
                  },
                  "howCreated": 0
                }
              ]
            },
            "singleVisual": {
              "visualType": "slicer",
              "objects": {
                "merge": {
                  "general": [
                    {
                      "properties": {
                        "filter": {
                          "filter": {
                            "Version": 2,
                            "From": [
                              {
                                "Name": "d",
                                "Entity": "Dim Extract Date",
                                "Type": 0
                              }
                            ],
                            "Where": [
                              {
                                "Condition": {
                                  "In": {
                                    "Expressions": [
                                      {
                                        "Column": {
                                          "Expression": {
                                            "SourceRef": {
                                              "Source": "d"
                                            }
                                          },
                                          "Property": "Slicer MMM YYYY"
                                        }
                                      }
                                    ],
                                    "Values": [
                                      [
                                        {
                                          "Literal": {
                                            "Value": "'Current Month'"
                                          }
                                        }
                                      ]
                                    ]
                                  }
                                }
                              }
                            ]
                          }
                        }
                      }
                    }
                  ],
                  "data": [
                    {
                      "properties": {
                        "mode": {
                          "expr": {
                            "Literal": {
                              "Value": "'Dropdown'"
                            }
                          }
                        }
                      }
                    }
                  ]
                }
              },
              "orderBy": [
                {
                  "Direction": 2,
                  "Expression": {
                    "Column": {
                      "Expression": {
                        "SourceRef": {
                          "Entity": "Dim Extract Date"
                        }
                      },
                      "Property": "Slicer MMM YYYY"
                    }
                  }
                }
              ],
              "activeProjections": {
                "Values": [
                  {
                    "Column": {
                      "Expression": {
                        "SourceRef": {
                          "Entity": "Dim Extract Date"
                        }
                      },
                      "Property": "Slicer MMM YYYY"
                    }
                  }
                ]
              }
            }
          },
          "b8f0e5e10b8ea026dd63": {
            "filters": {
              "byExpr": [
                {
                  "name": "771ae6c0ec0455806d80",
                  "type": "Categorical",
                  "expression": {
                    "Column": {
                      "Expression": {
                        "SourceRef": {
                          "Entity": "Fact Workforce"
                        }
                      },
                      "Property": "NeverStart Flag"
                    }
                  },
                  "howCreated": 0
                }
              ]
            },
            "singleVisual": {
              "visualType": "slicer",
              "objects": {
                "merge": {
                  "data": [
                    {
                      "properties": {
                        "mode": {
                          "expr": {
                            "Literal": {
                              "Value": "'Dropdown'"
                            }
                          }
                        }
                      }
                    }
                  ]
                }
              },
              "activeProjections": {
                "Values": [
                  {
                    "Column": {
                      "Expression": {
                        "SourceRef": {
                          "Entity": "Fact Workforce"
                        }
                      },
                      "Property": "NeverStart Flag"
                    }
                  }
                ]
              }
            }
          },
          "35ec6870ee140772c0b0": {
            "singleVisual": {
              "visualType": "shape",
              "objects": {}
            }
          },
          "2433926bad5242a561da": {
            "filters": {
              "byExpr": [
                {
                  "name": "370b9fdbc479c0650620",
                  "type": "Categorical",
                  "filter": {
                    "Version": 2,
                    "From": [
                      {
                        "Name": "d",
                        "Entity": "Dim Workforce Duplicates",
                        "Type": 0
                      }
                    ],
                    "Where": [
                      {
                        "Condition": {
                          "Not": {
                            "Expression": {
                              "In": {
                                "Expressions": [
                                  {
                                    "Column": {
                                      "Expression": {
                                        "SourceRef": {
                                          "Source": "d"
                                        }
                                      },
                                      "Property": "Member ID"
                                    }
                                  }
                                ],
                                "Values": [
                                  [
                                    {
                                      "Literal": {
                                        "Value": "null"
                                      }
                                    }
                                  ]
                                ]
                              }
                            }
                          }
                        }
                      }
                    ]
                  },
                  "expression": {
                    "Column": {
                      "Expression": {
                        "SourceRef": {
                          "Entity": "Dim Workforce Duplicates"
                        }
                      },
                      "Property": "Member ID"
                    }
                  },
                  "howCreated": 1
                },
                {
                  "name": "d1762fda19625ee2c518",
                  "type": "Categorical",
                  "expression": {
                    "Column": {
                      "Expression": {
                        "SourceRef": {
                          "Entity": "Fact Workforce"
                        }
                      },
                      "Property": "Source Entity"
                    }
                  },
                  "howCreated": 0
                },
                {
                  "name": "d0c3dfa8489bdb3b2abd",
                  "type": "Advanced",
                  "filter": {
                    "Version": 2,
                    "From": [
                      {
                        "Name": "d",
                        "Entity": "Dim Job History",
                        "Type": 0
                      }
                    ],
                    "Where": [
                      {
                        "Condition": {
                          "Comparison": {
                            "ComparisonKind": 0,
                            "Left": {
                              "Column": {
                                "Expression": {
                                  "SourceRef": {
                                    "Source": "d"
                                  }
                                },
                                "Property": "MemberLatestJobFlag"
                              }
                            },
                            "Right": {
                              "Literal": {
                                "Value": "0L"
                              }
                            }
                          }
                        }
                      }
                    ]
                  },
                  "expression": {
                    "Column": {
                      "Expression": {
                        "SourceRef": {
                          "Entity": "Dim Job History"
                        }
                      },
                      "Property": "MemberLatestJobFlag"
                    }
                  },
                  "howCreated": 1
                },
                {
                  "name": "1aee50f6b9e7bba107aa",
                  "type": "Categorical",
                  "expression": {
                    "Column": {
                      "Expression": {
                        "SourceRef": {
                          "Entity": "Dim Workforce Duplicates"
                        }
                      },
                      "Property": "Full name"
                    }
                  },
                  "howCreated": 0
                },
                {
                  "name": "48570092ae30b363028b",
                  "type": "Categorical",
                  "expression": {
                    "Column": {
                      "Expression": {
                        "SourceRef": {
                          "Entity": "Dim Workforce Duplicates"
                        }
                      },
                      "Property": "Termination reason"
                    }
                  },
                  "howCreated": 0
                },
                {
                  "name": "9ba01d60aafc6225f54b",
                  "type": "Categorical",
                  "expression": {
                    "Column": {
                      "Expression": {
                        "SourceRef": {
                          "Entity": "Dim Workforce Duplicates"
                        }
                      },
                      "Property": "Termination type"
                    }
                  },
                  "howCreated": 0
                },
                {
                  "name": "33bd6724f8c07422bccf",
                  "type": "Categorical",
                  "expression": {
                    "Column": {
                      "Expression": {
                        "SourceRef": {
                          "Entity": "Dim Workforce Duplicates"
                        }
                      },
                      "Property": "Visa type"
                    }
                  },
                  "howCreated": 0
                },
                {
                  "name": "cbe7d9d90c8dfdabfca0",
                  "type": "Categorical",
                  "expression": {
                    "Column": {
                      "Expression": {
                        "SourceRef": {
                          "Entity": "Dim Workforce Duplicates"
                        }
                      },
                      "Property": "Employee address postcode"
                    }
                  },
                  "howCreated": 0
                },
                {
                  "name": "683cdcc3d22471f5c68e",
                  "type": "Categorical",
                  "expression": {
                    "Column": {
                      "Expression": {
                        "SourceRef": {
                          "Entity": "Fact Workforce"
                        }
                      },
                      "Property": "Date of birth"
                    }
                  },
                  "howCreated": 0
                },
                {
                  "name": "f5fe054e2c62ab6f336d",
                  "type": "Categorical",
                  "expression": {
                    "Column": {
                      "Expression": {
                        "SourceRef": {
                          "Entity": "Dim Employment Start Date"
                        }
                      },
                      "Property": "Employement Start Date"
                    }
                  },
                  "howCreated": 0
                },
                {
                  "name": "58dfe28d0e009521d3aa",
                  "type": "Categorical",
                  "expression": {
                    "Column": {
                      "Expression": {
                        "SourceRef": {
                          "Entity": "Fact Workforce"
                        }
                      },
                      "Property": "NeverStart Flag"
                    }
                  },
                  "howCreated": 0
                },
                {
                  "name": "7312055eac908b2078f5",
                  "type": "Advanced",
                  "expression": {
                    "Column": {
                      "Expression": {
                        "SourceRef": {
                          "Entity": "Fact Workforce"
                        }
                      },
                      "Property": "Tax file number"
                    }
                  },
                  "howCreated": 0
                },
                {
                  "name": "5cccf70b8c4360921be3",
                  "type": "Categorical",
                  "expression": {
                    "Column": {
                      "Expression": {
                        "SourceRef": {
                          "Entity": "Fact Workforce"
                        }
                      },
                      "Property": "Member ID"
                    }
                  },
                  "howCreated": 0
                },
                {
                  "name": "5165e18662e39b4f35dd",
                  "type": "Categorical",
                  "expression": {
                    "Column": {
                      "Expression": {
                        "SourceRef": {
                          "Entity": "Dim Workforce"
                        }
                      },
                      "Property": "Employment status"
                    }
                  },
                  "howCreated": 0
                },
                {
                  "name": "8d7d7b16075b788cf12b",
                  "type": "Categorical",
                  "expression": {
                    "Column": {
                      "Expression": {
                        "SourceRef": {
                          "Entity": "Dim Workforce"
                        }
                      },
                      "Property": "Employing entity"
                    }
                  },
                  "howCreated": 0
                },
                {
                  "name": "cc310e91d5992856dbbd",
                  "type": "Categorical",
                  "expression": {
                    "Column": {
                      "Expression": {
                        "SourceRef": {
                          "Entity": "Dim Workforce"
                        }
                      },
                      "Property": "Gender"
                    }
                  },
                  "howCreated": 0
                },
                {
                  "name": "03f6c50cdfdfb688592c",
                  "type": "Categorical",
                  "expression": {
                    "Column": {
                      "Expression": {
                        "SourceRef": {
                          "Entity": "Dim Job History"
                        }
                      },
                      "Property": "Job title"
                    }
                  },
                  "howCreated": 0
                },
                {
                  "name": "f5194dbfe968c66859d5",
                  "type": "Categorical",
                  "expression": {
                    "Column": {
                      "Expression": {
                        "SourceRef": {
                          "Entity": "Dim Job History"
                        }
                      },
                      "Property": "Employment type"
                    }
                  },
                  "howCreated": 0
                }
              ]
            },
            "singleVisual": {
              "visualType": "tableEx",
              "objects": {}
            }
          },
          "2dc5f4664b7a121d00d4": {
            "filters": {
              "byExpr": [
                {
                  "name": "2a53259642a02c604e5c",
                  "type": "Categorical",
                  "filter": {
                    "Version": 2,
                    "From": [
                      {
                        "Name": "d",
                        "Entity": "Dim Workforce Duplicates",
                        "Type": 0
                      }
                    ],
                    "Where": [
                      {
                        "Condition": {
                          "Not": {
                            "Expression": {
                              "In": {
                                "Expressions": [
                                  {
                                    "Column": {
                                      "Expression": {
                                        "SourceRef": {
                                          "Source": "d"
                                        }
                                      },
                                      "Property": "Member ID"
                                    }
                                  }
                                ],
                                "Values": [
                                  [
                                    {
                                      "Literal": {
                                        "Value": "null"
                                      }
                                    }
                                  ]
                                ]
                              }
                            }
                          }
                        }
                      }
                    ]
                  },
                  "expression": {
                    "Column": {
                      "Expression": {
                        "SourceRef": {
                          "Entity": "Dim Workforce Duplicates"
                        }
                      },
                      "Property": "Member ID"
                    }
                  },
                  "howCreated": 1
                },
                {
                  "name": "cb6795f81e4dab6b5922",
                  "type": "Advanced",
                  "expression": {
                    "Measure": {
                      "Expression": {
                        "SourceRef": {
                          "Entity": "Fact Workforce"
                        }
                      },
                      "Property": "Count People"
                    }
                  },
                  "howCreated": 0
                }
              ]
            },
            "singleVisual": {
              "visualType": "cardVisual",
              "objects": {},
              "orderBy": [
                {
                  "Direction": 2,
                  "Expression": {
                    "Measure": {
                      "Expression": {
                        "SourceRef": {
                          "Entity": "Fact Workforce"
                        }
                      },
                      "Property": "Count People"
                    }
                  }
                }
              ]
            }
          },
          "03c70901003d0614c0ba": {
            "singleVisual": {
              "visualType": "textbox",
              "objects": {}
            }
          }
        },
        "visualContainerGroups": {
          "3743185304e282a60602": {
            "isHidden": false
          }
        }
      }
    },
    "objects": {
      "merge": {
        "outspacePane": [
          {
            "properties": {
              "expanded": {
                "expr": {
                  "Literal": {
                    "Value": "false"
                  }
                }
              }
            }
          }
        ]
      }
    }
  }
}